README.md
aliyunddns.py
setup.py
aliyunddns.egg-info/PKG-INFO
aliyunddns.egg-info/SOURCES.txt
aliyunddns.egg-info/dependency_links.txt
aliyunddns.egg-info/entry_points.txt
aliyunddns.egg-info/top_level.txt