Metadata-Version: 2.1
Name: aliyunddns
Version: 1.0
Summary: A dynamic DNS client for Aliyun written in pure Python
Home-page: https://github.com/koho/aliyunddns
Author: Gerhard Tan
Author-email: gerhard.gh.ta@gmail.com
License: UNKNOWN
Platform: UNKNOWN
